[
  {
    "spot_id": 32497,
    "issue_key": "WEB-162524",
    "website_url": "https://tacos-ensenada.com"
  },
  {
    "spot_id": 83970,
    "issue_key": "WEB-162496",
    "website_url": "https://cajjuneats.com/"
  },
  {
    "spot_id": 402172,
    "issue_key": "WEB-162120",
    "website_url": "https://www.jvspizzachester.com/"
  },
  {
    "spot_id": 78713,
    "issue_key": "WEB-162532",
    "website_url": "https://jmango.com"
  },
  {
    "spot_id": 355872,
    "issue_key": "WEB-162110",
    "website_url": "https://www.northsidepie.com/"
  },
  {
    "spot_id": 370801,
    "issue_key": "WEB-162134",
    "website_url": "https://fluid510.com/"
  },
  {
    "spot_id": 396693,
    "issue_key": "WEB-162480",
    "website_url": "http://shirazinc.com/"
  },
  {
    "spot_id": 386595,
    "issue_key": "WEB-162519",
    "website_url": "https://thecornbreadcafesc.com"
  },
  {
    "spot_id": 190846,
    "issue_key": "WEB-162497",
    "website_url": "https://marshallstreetbarandgrill.com"
  },
  {
    "spot_id": 266080,
    "issue_key": "WEB-162498",
    "website_url": "https://mesondeltaco.com"
  },
  {
    "spot_id": 228823,
    "issue_key": "WEB-162492",
    "website_url": "https://uniontavernseabreeze.com/"
  },
  {
    "spot_id": 100513,
    "issue_key": "WEB-152960",
    "website_url": "https://everestongrand.com"
  },
  {
    "spot_id": 95797,
    "issue_key": "WEB-162516",
    "website_url": "https://angelosofburien.com/"
  },
  {
    "spot_id": 326969,
    "issue_key": "WEB-162494",
    "website_url": "https://aracelylounge.com/"
  },
  {
    "spot_id": 329743,
    "issue_key": "WEB-161291",
    "website_url": "https://lousfullserv.com"
  },
  {
    "spot_id": 121320,
    "issue_key": "WEB-161260",
    "website_url": "https://districtoviedo.com"
  },
  {
    "spot_id": 216424,
    "issue_key": "WEB-162506",
    "website_url": "https://habanerosfreshmexcantina.com"
  },
  {
    "spot_id": 411345,
    "issue_key": "WEB-162518",
    "website_url": "https://hotdoghutkingsport.com/"
  },
  {
    "spot_id": 125154,
    "issue_key": "WEB-162499",
    "website_url": "http://chatterboxpleasantville.com/"
  },
  {
    "spot_id": 102069,
    "issue_key": "WEB-162393",
    "website_url": "http://losolivosabq.com"
  },
  {
    "spot_id": 156212,
    "issue_key": "WEB-162813",
    "website_url": "https://astirseattle.com"
  },
  {
    "spot_id": 135552,
    "issue_key": "WEB-161706",
    "website_url": "https://mamimonchitas.com"
  },
  {
    "spot_id": 414480,
    "issue_key": "WEB-162481",
    "website_url": "https://taleadc.com/"
  },
  {
    "spot_id": 385440,
    "issue_key": "WEB-162538",
    "website_url": "https://savoy1902.com"
  },
  {
    "spot_id": 391809,
    "issue_key": "WEB-161236",
    "website_url": "https://littlebsbbq.com"
  },
  {
    "spot_id": 190889,
    "issue_key": "WEB-155734",
    "website_url": "https://margaritasmexcantina.com"
  },
  {
    "spot_id": 205715,
    "issue_key": "WEB-137659",
    "website_url": "https://turfcateringkitchen.com/"
  },
  {
    "spot_id": 256773,
    "issue_key": "WEB-138264",
    "website_url": "https://hellothaibeavercreek.com"
  },
  {
    "spot_id": 389697,
    "issue_key": "WEB-162149",
    "website_url": "https://www.10empanadas.com/"
  },
  {
    "spot_id": 390159,
    "issue_key": "WEB-162903",
    "website_url": "https://nanaseats.com"
  },
  {
    "spot_id": 106695,
    "issue_key": "WEB-162814",
    "website_url": "https://sangamamseattle.com/"
  },
  {
    "spot_id": 188022,
    "issue_key": "WEB-162517",
    "website_url": "https://micavaandcocina.com"
  }
]